cookie/__init__.py
cookie/example.py
cookie_doh-0.0.13.dist-info/LICENSE
cookie_doh-0.0.13.dist-info/METADATA
cookie_doh-0.0.13.dist-info/WHEEL
cookie_doh-0.0.13.dist-info/RECORD
