Metadata-Version: 2.1
Name: cookie-doh
Version: 0.0.13
Summary: 
License: MIT
Author: microsoft
Requires-Python: >=3.10,<4.0
Classifier: License :: OSI Approved :: MIT License
Classifier: Programming Language :: Python :: 3
Classifier: Programming Language :: Python :: 3.10
Classifier: Programming Language :: Python :: 3.11
Classifier: Programming Language :: Python :: 3.12
